blender_wrapper/__init__.py
blender_wrapper/array_objects_by_curve.py
blender_wrapper/blender_bake_texture.py
blender_wrapper/blender_convert_textured_glb.py
blender_wrapper/blender_debug_wrapper.py
blender_wrapper/blender_file_converter.py
blender_wrapper/blender_generate_convex_hull.py
blender_wrapper/blender_modifier.py
blender_wrapper/blender_modifier_decimate.py
blender_wrapper/blender_reconstruct_mesh.py
blender_wrapper/blender_remove_doubles.py
blender_wrapper/blender_remove_material_slots.py
blender_wrapper/blender_resolve_bumpy_surface.py
blender_wrapper/blender_separate_mesh.py
blender_wrapper/blender_set_mesh_origin.py
blender_wrapper/blender_set_mesh_uvmap.py
blender_wrapper/blender_set_sharp_edge.py
blender_wrapper/blender_simplify_mesh.py
blender_wrapper/blender_wrapper.py
blender_wrapper/bpy_build_volume_mesh.py
blender_wrapper/create_road_junction.py
blender_wrapper/blender_header/__init__.py
blender_wrapper/blender_utils/Blender_enable_cuda.py
blender_wrapper/blender_utils/__init__.py
blender_wrapper/blender_utils/blender_const.py
blender_wrapper/blender_utils/blender_context_manager.py
blender_wrapper/blender_utils/blender_file_loader.py
blender_wrapper/blender_utils/blender_remesh_opt.py
blender_wrapper/blender_utils/blender_resolve_bumpy_surface.py
blender_wrapper/blender_utils/fill_hole.py
blender_wrapper/utils/__init__.py
blender_wrapper/utils/runtime.py
blender_wrapper/utils/singleton.py
blender_wrapper-0.1.24.dist-info/LICENSE
blender_wrapper-0.1.24.dist-info/METADATA
blender_wrapper-0.1.24.dist-info/WHEEL
blender_wrapper-0.1.24.dist-info/top_level.txt
blender_wrapper-0.1.24.dist-info/RECORD
