Metadata-Version: 2.1
Name: blender_wrapper
Version: 0.1.24
Summary: Utility tools for blender. Execute some automation tasks by running background blender process.
Home-page: https://github.com/ImagineersHub/blender-wrapper
Author: esunvoteb
Author-email: esun@voteb.com
License: MIT
Keywords: python,blender
Classifier: Development Status :: 3 - Alpha
Classifier: Intended Audience :: Developers
Classifier: Topic :: Software Development :: Build Tools
Classifier: License :: OSI Approved :: MIT License
Classifier: Programming Language :: Python :: 3.10
License-File: LICENSE
Requires-Dist: fake-bpy-module-latest
